setup.cfg
setup.py
MatQQv2/MatQUBOa.py
MatQQv2/__init__.py
MatQQv2.egg-info/PKG-INFO
MatQQv2.egg-info/SOURCES.txt
MatQQv2.egg-info/dependency_links.txt
MatQQv2.egg-info/not-zip-safe
MatQQv2.egg-info/requires.txt
MatQQv2.egg-info/top_level.txt